predictitpy.py
setup.cfg
setup.py
predictitpy.egg-info/PKG-INFO
predictitpy.egg-info/SOURCES.txt
predictitpy.egg-info/dependency_links.txt
predictitpy.egg-info/not-zip-safe
predictitpy.egg-info/top_level.txt