Metadata-Version: 1.0
Name: predictitpy
Version: 0.2
Summary: A very light wrapper around the PredictIt.org market data api.
Home-page: https://github.com/adamjoshuagray/predictitpy
Author: Adam J. Gray
Author-email: adam.joshua.gray@gmail.com
License: MIT
Platform: UNKNOWN
